word_image
