Metadata-Version: 2.1
Name: word-image
Version: 0.1.3
Summary: Generate images of words with configurable augmentation options
Home-page: https://github.com/econser/word_image
Download-URL: https://github.com/econser/word_image/archive/refs/tags/v_0_1_3.tar.gz
Author: econser
Author-email: econser@gmail.com
License: MIT
Keywords: contrastive learning,computer vision,image augmentation
Classifier: License :: OSI Approved :: MIT License
Classifier: Intended Audience :: Developers
Classifier: Intended Audience :: Science/Research
Classifier: Topic :: Scientific/Engineering :: Artificial Intelligence
Classifier: Programming Language :: Python :: 3 :: Only
License-File: LICENSE
